dynamorm/__init__.py
dynamorm/exceptions.py
dynamorm/indexes.py
dynamorm/local.py
dynamorm/model.py
dynamorm/relationships.py
dynamorm/signals.py
dynamorm/table.py
dynamorm/types/__init__.py
dynamorm/types/_marshmallow.py
dynamorm/types/_schematics.py
dynamorm/types/base.py
dynamorm-0.11.0.dist-info/LICENSE
dynamorm-0.11.0.dist-info/METADATA
dynamorm-0.11.0.dist-info/WHEEL
dynamorm-0.11.0.dist-info/top_level.txt
dynamorm-0.11.0.dist-info/RECORD
