Metadata-Version: 2.1
Name: dynamorm
Version: 0.11.0
Summary: DynamORM is a Python object & relation mapping library for Amazon's DynamoDB service.
Home-page: https://github.com/NerdWalletOSS/DynamORM
Author: Evan Borgstrom
Author-email: evan@borgstrom.ca
License: Apache License Version 2.0
Platform: UNKNOWN
Classifier: Development Status :: 4 - Beta
Classifier: Programming Language :: Python :: 2.7
Classifier: Programming Language :: Python :: 3.5
Classifier: Programming Language :: Python :: 3.6
Classifier: Programming Language :: Python :: 3.7
Classifier: Programming Language :: Python :: 3.8
Classifier: Intended Audience :: Developers
Classifier: License :: OSI Approved :: Apache Software License
Classifier: Natural Language :: English
Classifier: Programming Language :: Python
Classifier: Topic :: Database
Classifier: Topic :: Internet
Classifier: Topic :: Software Development :: Libraries
Requires-Python: >=2.7, !=3.0.*, !=3.1.*, !=3.2.*, !=3.3.*, !=3.4.*, <4
Provides-Extra: marshmallow
Provides-Extra: schematics
